MANIFEST.in
README.md
setup.cfg
setup.py
dtrange/Datetime.py
dtrange/__init__.py
dtrange/bounds.py
dtrange/calendar.py
dtrange/drange.py
dtrange/dtrange.py
dtrange/fraction.py
dtrange/trange.py
dtrange/utils.py
dtrange.egg-info/PKG-INFO
dtrange.egg-info/SOURCES.txt
dtrange.egg-info/dependency_links.txt
dtrange.egg-info/top_level.txt