Metadata-Version: 1.1
Name: dtrange
Version: 1.2.2
Summary: Multi-calendar datetime, date, and time range iterators.
Home-page: https://www.github.com/rsmz/dtrange
Author: Remik Ziemlinski
Author-email: first.last@gmail.com
License: GPLv3
Download-URL: https://github.com/rsmz/dtrange/archive/dtrange-1.2.2.tar.gz
Platform: UNKNOWN
